UofSC_Calc_Labs/__init__.py
solve_for_x/__init__.py
uofsc_calculus_labs/__init__.py
uofsc_calculus_labs-0.3.dist-info/METADATA
uofsc_calculus_labs-0.3.dist-info/WHEEL
uofsc_calculus_labs-0.3.dist-info/top_level.txt
uofsc_calculus_labs-0.3.dist-info/RECORD
