Metadata-Version: 2.1
Name: uofsc-calculus-labs
Version: 0.3
Summary: A collection of functions for UofSC Calculus Labs
Home-page: UNKNOWN
Author: Cuyler Warnock
Author-email: cwarnock@math.sc.edu
License: GPLv2+
Keywords: SageMath packaging
Platform: UNKNOWN
Classifier: Development Status :: 4 - Beta
Classifier: Topic :: Software Development :: Build Tools
Classifier: Topic :: Scientific/Engineering :: Mathematics
Classifier: License :: OSI Approved :: GNU General Public License v2 or later (GPLv2+)
Classifier: Programming Language :: Python :: 3.7
Requires-Dist: sage-package
Requires-Dist: sphinx
